ds_sqlwhat/State.py
ds_sqlwhat/__init__.py
ds_sqlwhat/sct_syntax.py
ds_sqlwhat/test_exercise.py
ds_sqlwhat/checks/__init__.py
ds_sqlwhat/checks/check_funcs.py
ds_sqlwhat/checks/has_funcs.py
ds_sqlwhat-3.8.4.dist-info/LICENSE
ds_sqlwhat-3.8.4.dist-info/METADATA
ds_sqlwhat-3.8.4.dist-info/WHEEL
ds_sqlwhat-3.8.4.dist-info/top_level.txt
ds_sqlwhat-3.8.4.dist-info/RECORD
