Metadata-Version: 2.1
Name: ds-sqlwhat
Version: 3.8.4
Summary: Submission correctness tests for SQL
Home-page: https://github.com/datacamp/sqlwhat
Author: Michael Chow, Filip Schouwenaars
Author-email: michael@datacamp.com
Maintainer: Jeroen Hermans
Maintainer-email: content-engineering@datacamp.com
Classifier: Programming Language :: Python :: 3
Classifier: License :: OSI Approved :: GNU Affero General Public License v3
Classifier: Operating System :: OS Independent
License-File: LICENSE
Requires-Dist: antlr-plsql (~=0.9.1)
Requires-Dist: antlr-tsql (~=0.12.6)
Requires-Dist: markupsafe (==2.0.1)
Requires-Dist: russian-protowhat (~=1.13.0)
